py_terminal/LocalTerminal.py
py_terminal/RemoteTerminal.py
py_terminal/__init__.py
py_terminal/_base.py
py_terminal/exception.py
py_terminal/test.py
PyCmdTerminal-0.1.17.dist-info/LICENSE
PyCmdTerminal-0.1.17.dist-info/METADATA
PyCmdTerminal-0.1.17.dist-info/WHEEL
PyCmdTerminal-0.1.17.dist-info/top_level.txt
PyCmdTerminal-0.1.17.dist-info/RECORD
