Metadata-Version: 2.1
Name: PyCmdTerminal
Version: 0.1.17
Summary: py-terminal integrates local and remote terminal operations.
Home-page: https://github.com/Xg-dong/python-terminal
Author: cainiao dong
Author-email: xunxiangdong@qq.com
Classifier: Programming Language :: Python :: 3
Classifier: License :: OSI Approved :: Apache Software License
Classifier: Operating System :: OS Independent
Classifier: Programming Language :: Python :: 3.6
Classifier: Programming Language :: Python :: 3.7
Classifier: Programming Language :: Python :: 3.8
Classifier: Programming Language :: Python :: 3.9
Classifier: Programming Language :: Python :: 3.10
Requires-Python: >=3.6
License-File: LICENSE
Requires-Dist: paramiko
